crit_est/__init__.py
crit_est/criterion.py
crit_est-0.2.0.dist-info/METADATA
crit_est-0.2.0.dist-info/WHEEL
crit_est-0.2.0.dist-info/top_level.txt
crit_est-0.2.0.dist-info/RECORD
