Metadata-Version: 2.1
Name: crit-est
Version: 0.2.0
Summary: The criterion-based estimation tools
Author: Alexander Smirnov
Author-email: alexsm.w@yandex.ru
